LICENSE.txt
MANIFEST.in
README.md
clear.sh
setup.cfg
setup.py
doc/epydoc.conf
doc/epydoc.sh
doc/snakemq.mm
doc/sphinx/Makefile
doc/sphinx/source/api.rst
doc/sphinx/source/changelog.rst
doc/sphinx/source/conf.py
doc/sphinx/source/index.rst
doc/sphinx/source/tutorial.rst
doc/sphinx/source/_templates/layout.html
doc/sphinx/source/api/link.rst
doc/sphinx/source/api/messaging.rst
doc/sphinx/source/api/packeter.rst
examples/messaging_connector.py
examples/messaging_listener.py
examples/packeter_connector.py
examples/packeter_listener.py
examples/rpc1_connector.py
examples/rpc1_listener.py
snakeMQ.egg-info/PKG-INFO
snakeMQ.egg-info/SOURCES.html
snakeMQ.egg-info/SOURCES.txt
snakeMQ.egg-info/dependency_links.html
snakeMQ.egg-info/dependency_links.txt
snakeMQ.egg-info/top_level.html
snakeMQ.egg-info/top_level.txt
snakemq/__init__.py
snakemq/buffers.py
snakemq/callbacks.py
snakemq/dummyssl.py
snakemq/exceptions.py
snakemq/link.py
snakemq/message.py
snakemq/messaging.py
snakemq/packeter.py
snakemq/poll.py
snakemq/pollbell.py
snakemq/queues.py
snakemq/rpc.py
snakemq/throttle.py
snakemq/version.py
snakemq/storage/__init__.py
snakemq/storage/gadfly.py
snakemq/storage/mongodb.py
snakemq/storage/sqla.py
snakemq/storage/sqlite.py
tests/__init__.py
tests/performance/packeter_connections.py
tests/performance/packeter_multiple_small.py
tests/performance/packeter_single_large.py
tests/srcchecks/pylint.rc
tests/srcchecks/run.sh
tests/unittests/__init__.py
tests/unittests/run.py
tests/unittests/testcert.pem
tests/unittests/testkey.pem
tests/unittests/tests_buffers.py
tests/unittests/tests_link.py
tests/unittests/tests_messaging.py
tests/unittests/tests_packeter.py
tests/unittests/tests_queues.py
tests/unittests/tests_rpc.py
tests/unittests/utils.py